dicergirl/coc/__init__.py
dicergirl/coc/coccards.py
dicergirl/coc/cocutils.py
dicergirl/coc/investigator.py
dicergirl/coc/madness.py
dicergirl/coc/nbhandlers.py
dicergirl/plugins/coc/__init__.py
dicergirl/plugins/coc/backend.py
dicergirl/plugins/coc/cards.py
dicergirl/plugins/coc/coccards.py
dicergirl/plugins/coc/cocutils.py
dicergirl/plugins/coc/handlers.py
dicergirl/plugins/coc/initialize.py
dicergirl/plugins/coc/investigator.py
dicergirl/plugins/coc/madness.py
dicergirl/plugins/coc/nbhandlers.py
dicergirl/plugins/diviner/__init__.py
dicergirl/plugins/diviner/handlers.py
dicergirl/plugins/diviner/nbhandlers.py
dicergirl/plugins/diviner/utils.py
dicergirl_plugin_diviner-2.0.0.dist-info/LICENSE
dicergirl_plugin_diviner-2.0.0.dist-info/METADATA
dicergirl_plugin_diviner-2.0.0.dist-info/WHEEL
dicergirl_plugin_diviner-2.0.0.dist-info/top_level.txt
dicergirl_plugin_diviner-2.0.0.dist-info/RECORD
